{
    "floor": {
        "x": 96,
        "y": 0,
        "width": 64,
        "height": 48,
        "sliceX": 4,
        "sliceY": 3
    },
    "wall_top": {
        "x": 16,
        "y": 0,
        "width": 64,
        "height": 16,
        "sliceX": 4,
        "sliceY": 1
    },
    "wall_bottom": {
        "x": 16,
        "y": 64,
        "width": 64,
        "height": 16,
        "sliceX": 4,
        "sliceY": 1
    },
    "wall_left": {
        "x": 0,
        "y": 0,
        "width": 16,
        "height": 64,
        "sliceX": 1,
        "sliceY": 4
    },
    "wall_right": {
        "x": 80,
        "y": 0,
        "width": 16,
        "height": 64,
        "sliceX": 1,
        "sliceY": 4
    },
    "wall_bottom_left": {
        "x": 0,
        "y": 64,
        "width": 16,
        "height": 16
    },
    "wall_bottom_right": {
        "x": 80,
        "y": 64,
        "width": 16,
        "height": 16
    }
}
